_ncrystal_pypluginmgr/__init__.py
_ncrystal_pypluginmgr/_argmode.py
_ncrystal_pypluginmgr/cli.py
ncrystal_pypluginmgr-0.0.5.dist-info/LICENSE
ncrystal_pypluginmgr-0.0.5.dist-info/METADATA
ncrystal_pypluginmgr-0.0.5.dist-info/WHEEL
ncrystal_pypluginmgr-0.0.5.dist-info/entry_points.txt
ncrystal_pypluginmgr-0.0.5.dist-info/top_level.txt
ncrystal_pypluginmgr-0.0.5.dist-info/RECORD
