Metadata-Version: 2.2
Name: ncrystal-pypluginmgr
Version: 0.0.5
Summary: Plugin manager for NCrystal.
Author: NCrystal developers (Thomas Kittelmann, Xiao Xiao Cai)
License: The Apache 2.0 license is reproduced in the following. See the NOTICE file for
Project-URL: Homepage, https://mctools.github.io/ncrystal/
Project-URL: Bug Tracker, https://github.com/mctools/ncrystal/issues
Classifier: Programming Language :: Python :: 3
Classifier: License :: OSI Approved :: Apache Software License
Requires-Python: >=3.8
License-File: LICENSE
